odoo/addons/mrp_order_report_lot_reserved/README.rst
odoo/addons/mrp_order_report_lot_reserved/__init__.py
odoo/addons/mrp_order_report_lot_reserved/__manifest__.py
odoo/addons/mrp_order_report_lot_reserved/i18n/it.po
odoo/addons/mrp_order_report_lot_reserved/i18n/mrp_order_report_lot_reserved.pot
odoo/addons/mrp_order_report_lot_reserved/models/__init__.py
odoo/addons/mrp_order_report_lot_reserved/models/stock_move.py
odoo/addons/mrp_order_report_lot_reserved/readme/CONTRIBUTORS.rst
odoo/addons/mrp_order_report_lot_reserved/readme/DESCRIPTION.rst
odoo/addons/mrp_order_report_lot_reserved/reports/mrp_order_report.xml
odoo/addons/mrp_order_report_lot_reserved/static/description/icon.png
odoo/addons/mrp_order_report_lot_reserved/static/description/index.html
odoo_addon_mrp_order_report_lot_reserved-16.0.1.0.0.4.dist-info/METADATA
odoo_addon_mrp_order_report_lot_reserved-16.0.1.0.0.4.dist-info/WHEEL
odoo_addon_mrp_order_report_lot_reserved-16.0.1.0.0.4.dist-info/top_level.txt
odoo_addon_mrp_order_report_lot_reserved-16.0.1.0.0.4.dist-info/RECORD
